morpc/__init__.py
morpc/geocode.py
morpc/logs.py
morpc/morpc.py
morpc/req.py
morpc/census/__init__.py
morpc/census/acs_variable_groups.json
morpc/census/acs_variable_groups_v2.json
morpc/census/api.py
morpc/census/census.py
morpc/census/geos.py
morpc/census/tigerweb.py
morpc/color/__init__.py
morpc/color/color.py
morpc/color/morpc_colors.json
morpc/color/palette.py
morpc/color/.ipynb_checkpoints/color-checkpoint.py
morpc/color/.ipynb_checkpoints/morpc_colors-checkpoint.json
morpc/frictionless/__init__.py
morpc/frictionless/frictionless.py
morpc/plot/__init__.py
morpc/plot/map.py
morpc/plot/plot.py
morpc/rest_api/.gitignore
morpc/rest_api/__init__.py
morpc/rest_api/rest_api.py
morpc-0.4.2.dist-info/METADATA
morpc-0.4.2.dist-info/WHEEL
morpc-0.4.2.dist-info/top_level.txt
morpc-0.4.2.dist-info/RECORD
