Metadata-Version: 2.4
Name: morpc
Version: 0.4.2
Summary: Data managment tools used by MORPC
Author-email: MORPC data team <dataandmaps@morpc.org>
License-Expression: MIT
Classifier: Development Status :: 1 - Planning
Classifier: Intended Audience :: Developers
Requires-Python: >=3.10
Requires-Dist: requests
Requires-Dist: pandas
Requires-Dist: geopandas
Requires-Dist: frictionless
Requires-Dist: shapely
Requires-Dist: IPython
Requires-Dist: xlsxwriter
Requires-Dist: plotnine
